{
  "$schema": "https://charm.land/crush.json",
  "lsp": {
    "rust_analyzer": {
      "command": "rust-analyzer",
      "disabled": false,
      "root_markers": ["Cargo.toml"]
    },
    "rls": {
      "disabled": true
    }
  },
  "tools": {
    "ls": {}
  },
  "options": {
    "debug": true,
    "debug_lsp": true
  },
  "mcp": {
    "shamir-db": {
      "type": "stdio",
      "env": {
        "IJ_MCP_SERVER_PORT": "64342"
      },
      "command": "C:\\Program Files\\JetBrains\\RustRover 2025.3.1\\jbr\\bin\\java",
      "args": [
        "-classpath",
        "C:\\Program Files\\JetBrains\\RustRover 2025.3.1\\plugins\\mcpserver\\lib\\mcpserver-frontend.jar;C:\\Program Files\\JetBrains\\RustRover 2025.3.1\\lib\\util-8.jar;C:\\Program Files\\JetBrains\\RustRover 2025.3.1\\lib\\module-intellij.libraries.ktor.client.cio.jar;C:\\Program Files\\JetBrains\\RustRover 2025.3.1\\lib\\module-intellij.libraries.ktor.client.jar;C:\\Program Files\\JetBrains\\RustRover 2025.3.1\\lib\\module-intellij.libraries.ktor.network.tls.jar;C:\\Program Files\\JetBrains\\RustRover 2025.3.1\\lib\\module-intellij.libraries.ktor.io.jar;C:\\Program Files\\JetBrains\\RustRover 2025.3.1\\lib\\module-intellij.libraries.ktor.utils.jar;C:\\Program Files\\JetBrains\\RustRover 2025.3.1\\lib\\module-intellij.libraries.kotlinx.io.jar;C:\\Program Files\\JetBrains\\RustRover 2025.3.1\\lib\\module-intellij.libraries.kotlinx.serialization.core.jar;C:\\Program Files\\JetBrains\\RustRover 2025.3.1\\lib\\module-intellij.libraries.kotlinx.serialization.json.jar",
        "com.intellij.mcpserver.stdio.McpStdioRunnerKt"
      ]
    }
  }
}